{
  "table_info": {
    "table_columns": [
      "date",
      "label",
      "month",
      "quarter",
      "sourceDataset",
      "updateDate",
      "value",
      "year"
    ],
    "table_samples": [
      {
        "date": "1989 JAN",
        "label": "1989 JAN",
        "month": "January",
        "quarter": NaN,
        "sourceDataset": "MM23",
        "updateDate": "2019-04-16T23:00:00.000Z",
        "value": 4.0,
        "year": 1989
      },
      {
        "date": "1998 JAN",
        "label": "1998 JAN",
        "month": "January",
        "quarter": NaN,
        "sourceDataset": "MM23",
        "updateDate": "2015-10-12T23:00:00.000Z",
        "value": -0.7,
        "year": 1998
      },
      {
        "date": "1999 JUN",
        "label": "1999 JUN",
        "month": "June",
        "quarter": NaN,
        "sourceDataset": "MM23",
        "updateDate": "2015-10-12T23:00:00.000Z",
        "value": -2.0,
        "year": 1999
      },
      {
        "date": "1993 DEC",
        "label": "1993 DEC",
        "month": "December",
        "quarter": NaN,
        "sourceDataset": "MM23",
        "updateDate": "2019-04-16T23:00:00.000Z",
        "value": 0.4,
        "year": 1993
      },
      {
        "date": "2006 NOV",
        "label": "2006 NOV",
        "month": "November",
        "quarter": NaN,
        "sourceDataset": "MM23",
        "updateDate": "2015-10-12T23:00:00.000Z",
        "value": -1.1,
        "year": 2006
      }
    ]
  },
  "nl_utterance": "Create a trend chart showing the change in values over the dates given.",
  "refer_fileds": [
    {
      "field": "date",
      "type": "temporal"
    },
    {
      "field": "value",
      "type": "quantitative"
    }
  ],
  "refer_others": [],
  "generated_chart_list": [
    {
      "mark": "line",
      "encoding": {
        "x": {
          "field": "date",
          "type": "temporal"
        },
        "y": {
          "field": "value",
          "type": "quantitative"
        }
      }
    },
    {
      "mark": "area",
      "encoding": {
        "x": {
          "field": "date",
          "type": "temporal"
        },
        "y": {
          "field": "value",
          "type": "quantitative"
        }
      }
    },
    {
      "mark": "point",
      "encoding": {
        "x": {
          "field": "date",
          "type": "temporal"
        },
        "y": {
          "field": "value",
          "type": "quantitative"
        }
      }
    },
    {
      "mark": "point",
      "encoding": {
        "x": {
          "field": "value",
          "type": "quantitative"
        },
        "y": {
          "field": "date",
          "type": "temporal"
        }
      }
    }
  ]
}