{
  "table_info": {
    "table_columns": [
      "date",
      "label",
      "month",
      "quarter",
      "sourceDataset",
      "updateDate",
      "value",
      "year"
    ],
    "table_samples": [
      {
        "date": "2015 FEB",
        "label": "2015 FEB",
        "month": "February",
        "quarter": NaN,
        "sourceDataset": "MM23",
        "updateDate": "2017-03-14T00:00:00.000Z",
        "value": 2.1,
        "year": 2015
      },
      {
        "date": "2016 JUN",
        "label": "2016 JUN",
        "month": "June",
        "quarter": NaN,
        "sourceDataset": "MM23",
        "updateDate": "2017-03-14T00:00:00.000Z",
        "value": -0.2,
        "year": 2016
      },
      {
        "date": "2018 JUN",
        "label": "2018 JUN",
        "month": "June",
        "quarter": NaN,
        "sourceDataset": "MM23",
        "updateDate": "2018-07-17T23:00:00.000Z",
        "value": -1.3,
        "year": 2018
      },
      {
        "date": "2018 SEP",
        "label": "2018 SEP",
        "month": "September",
        "quarter": NaN,
        "sourceDataset": "MM23",
        "updateDate": "2018-10-16T23:00:00.000Z",
        "value": 1.9,
        "year": 2018
      },
      {
        "date": "2017 DEC",
        "label": "2017 DEC",
        "month": "December",
        "quarter": NaN,
        "sourceDataset": "MM23",
        "updateDate": "2018-01-16T00:00:00.000Z",
        "value": -1.1,
        "year": 2017
      }
    ]
  },
  "nl_utterance": "Show me a chart with the quantitative values from the dataset.",
  "refer_fileds": [
    {
      "field": "value",
      "type": "quantitative"
    }
  ],
  "refer_others": [],
  "generated_chart_list": [
    {
      "mark": "boxplot",
      "encoding": {
        "y": {
          "field": "value",
          "type": "quantitative"
        }
      }
    }
  ]
}