{
  "table_info": {
    "table_columns": [
      "catX",
      "x",
      "y"
    ],
    "table_samples": [
      {
        "catX": 1,
        "x": 1,
        "y": 1
      },
      {
        "catX": 67,
        "x": 67,
        "y": 67
      },
      {
        "catX": 56,
        "x": 56,
        "y": 56
      },
      {
        "catX": 47,
        "x": 47,
        "y": 47
      },
      {
        "catX": 81,
        "x": 81,
        "y": 81
      }
    ]
  },
  "nl_utterance": "Create a chart displaying 'catX' along with 'y' values.",
  "refer_fileds": [
    {
      "field": "catX",
      "type": "quantitative"
    },
    {
      "field": "y",
      "type": "quantitative"
    }
  ],
  "refer_others": [],
  "generated_chart_list": [
    {
      "mark": "bar",
      "encoding": {
        "x": {
          "field": "catX",
          "type": "quantitative",
          "bin": true
        },
        "y": {
          "field": "y",
          "type": "quantitative",
          "aggregate": "sum"
        }
      }
    },
    {
      "mark": "bar",
      "encoding": {
        "x": {
          "field": "catX",
          "type": "quantitative",
          "bin": true
        },
        "y": {
          "field": "y",
          "type": "quantitative",
          "aggregate": "mean"
        }
      }
    },
    {
      "mark": "bar",
      "encoding": {
        "x": {
          "field": "y",
          "type": "quantitative",
          "bin": true
        },
        "y": {
          "field": "catX",
          "type": "quantitative",
          "aggregate": "sum"
        }
      }
    },
    {
      "mark": "bar",
      "encoding": {
        "x": {
          "field": "y",
          "type": "quantitative",
          "bin": true
        },
        "y": {
          "field": "catX",
          "type": "quantitative",
          "aggregate": "mean"
        }
      }
    },
    {
      "mark": "point",
      "encoding": {
        "x": {
          "field": "catX",
          "type": "quantitative"
        },
        "y": {
          "field": "y",
          "type": "quantitative"
        }
      }
    },
    {
      "mark": "point",
      "encoding": {
        "x": {
          "field": "y",
          "type": "quantitative"
        },
        "y": {
          "field": "catX",
          "type": "quantitative"
        }
      }
    }
  ]
}