{
  "table_info": {
    "table_columns": [
      "country",
      "medianIncome",
      "meanIncome",
      "gdpPerCapitaPPP",
      "pop2022"
    ],
    "table_samples": [
      {
        "country": "Luxembourg",
        "medianIncome": 26321,
        "meanIncome": 31376,
        "gdpPerCapitaPPP": 124590.0,
        "pop2022": 647599
      },
      {
        "country": "Turkmenistan",
        "medianIncome": 706,
        "meanIncome": 963,
        "gdpPerCapitaPPP": 15206.0,
        "pop2022": 6430770
      },
      {
        "country": "Sierra Leone",
        "medianIncome": 765,
        "meanIncome": 1004,
        "gdpPerCapitaPPP": 1794.0,
        "pop2022": 8605718
      },
      {
        "country": "Brazil",
        "medianIncome": 4559,
        "meanIncome": 7654,
        "gdpPerCapitaPPP": 15299.0,
        "pop2022": 215313498
      },
      {
        "country": "Armenia",
        "medianIncome": 2216,
        "meanIncome": 2810,
        "gdpPerCapitaPPP": 14257.0,
        "pop2022": 2780469
      }
    ]
  },
  "nl_utterance": "Show me a scatter plot that illustrates the correlation between median income and the population for 2022.",
  "refer_fileds": [
    {
      "field": [
        "gdpPerCapitaPPP",
        "medianIncome",
        "meanIncome"
      ],
      "type": "quantitative"
    },
    {
      "field": "medianIncome",
      "type": "quantitative"
    },
    {
      "field": "pop2022",
      "type": "quantitative"
    }
  ],
  "refer_others": [],
  "generated_chart_list": [
    {
      "mark": "point",
      "encoding": {
        "x": {
          "field": "gdpPerCapitaPPP",
          "type": "quantitative"
        },
        "y": {
          "field": "medianIncome",
          "type": "quantitative"
        },
        "size": {
          "field": "pop2022",
          "type": "quantitative"
        }
      }
    },
    {
      "mark": "point",
      "encoding": {
        "x": {
          "field": "medianIncome",
          "type": "quantitative"
        },
        "y": {
          "field": "medianIncome",
          "type": "quantitative"
        },
        "size": {
          "field": "pop2022",
          "type": "quantitative"
        }
      }
    },
    {
      "mark": "point",
      "encoding": {
        "x": {
          "field": "meanIncome",
          "type": "quantitative"
        },
        "y": {
          "field": "medianIncome",
          "type": "quantitative"
        },
        "size": {
          "field": "pop2022",
          "type": "quantitative"
        }
      }
    },
    {
      "mark": "point",
      "encoding": {
        "x": {
          "field": "gdpPerCapitaPPP",
          "type": "quantitative"
        },
        "y": {
          "field": "pop2022",
          "type": "quantitative"
        },
        "size": {
          "field": "medianIncome",
          "type": "quantitative"
        }
      }
    },
    {
      "mark": "point",
      "encoding": {
        "x": {
          "field": "medianIncome",
          "type": "quantitative"
        },
        "y": {
          "field": "pop2022",
          "type": "quantitative"
        },
        "size": {
          "field": "medianIncome",
          "type": "quantitative"
        }
      }
    },
    {
      "mark": "point",
      "encoding": {
        "x": {
          "field": "meanIncome",
          "type": "quantitative"
        },
        "y": {
          "field": "pop2022",
          "type": "quantitative"
        },
        "size": {
          "field": "medianIncome",
          "type": "quantitative"
        }
      }
    },
    {
      "mark": "point",
      "encoding": {
        "x": {
          "field": "medianIncome",
          "type": "quantitative"
        },
        "y": {
          "field": "gdpPerCapitaPPP",
          "type": "quantitative"
        },
        "size": {
          "field": "pop2022",
          "type": "quantitative"
        }
      }
    },
    {
      "mark": "point",
      "encoding": {
        "x": {
          "field": "medianIncome",
          "type": "quantitative"
        },
        "y": {
          "field": "medianIncome",
          "type": "quantitative"
        },
        "size": {
          "field": "pop2022",
          "type": "quantitative"
        }
      }
    },
    {
      "mark": "point",
      "encoding": {
        "x": {
          "field": "medianIncome",
          "type": "quantitative"
        },
        "y": {
          "field": "meanIncome",
          "type": "quantitative"
        },
        "size": {
          "field": "pop2022",
          "type": "quantitative"
        }
      }
    },
    {
      "mark": "point",
      "encoding": {
        "x": {
          "field": "medianIncome",
          "type": "quantitative"
        },
        "y": {
          "field": "pop2022",
          "type": "quantitative"
        },
        "size": {
          "field": "gdpPerCapitaPPP",
          "type": "quantitative"
        }
      }
    },
    {
      "mark": "point",
      "encoding": {
        "x": {
          "field": "medianIncome",
          "type": "quantitative"
        },
        "y": {
          "field": "pop2022",
          "type": "quantitative"
        },
        "size": {
          "field": "medianIncome",
          "type": "quantitative"
        }
      }
    },
    {
      "mark": "point",
      "encoding": {
        "x": {
          "field": "medianIncome",
          "type": "quantitative"
        },
        "y": {
          "field": "pop2022",
          "type": "quantitative"
        },
        "size": {
          "field": "meanIncome",
          "type": "quantitative"
        }
      }
    },
    {
      "mark": "point",
      "encoding": {
        "x": {
          "field": "pop2022",
          "type": "quantitative"
        },
        "y": {
          "field": "gdpPerCapitaPPP",
          "type": "quantitative"
        },
        "size": {
          "field": "medianIncome",
          "type": "quantitative"
        }
      }
    },
    {
      "mark": "point",
      "encoding": {
        "x": {
          "field": "pop2022",
          "type": "quantitative"
        },
        "y": {
          "field": "medianIncome",
          "type": "quantitative"
        },
        "size": {
          "field": "medianIncome",
          "type": "quantitative"
        }
      }
    },
    {
      "mark": "point",
      "encoding": {
        "x": {
          "field": "pop2022",
          "type": "quantitative"
        },
        "y": {
          "field": "meanIncome",
          "type": "quantitative"
        },
        "size": {
          "field": "medianIncome",
          "type": "quantitative"
        }
      }
    },
    {
      "mark": "point",
      "encoding": {
        "x": {
          "field": "pop2022",
          "type": "quantitative"
        },
        "y": {
          "field": "medianIncome",
          "type": "quantitative"
        },
        "size": {
          "field": "gdpPerCapitaPPP",
          "type": "quantitative"
        }
      }
    },
    {
      "mark": "point",
      "encoding": {
        "x": {
          "field": "pop2022",
          "type": "quantitative"
        },
        "y": {
          "field": "medianIncome",
          "type": "quantitative"
        },
        "size": {
          "field": "medianIncome",
          "type": "quantitative"
        }
      }
    },
    {
      "mark": "point",
      "encoding": {
        "x": {
          "field": "pop2022",
          "type": "quantitative"
        },
        "y": {
          "field": "medianIncome",
          "type": "quantitative"
        },
        "size": {
          "field": "meanIncome",
          "type": "quantitative"
        }
      }
    },
    {
      "mark": "rect",
      "encoding": {
        "x": {
          "field": "gdpPerCapitaPPP",
          "type": "quantitative",
          "bin": true
        },
        "y": {
          "field": "medianIncome",
          "type": "quantitative",
          "bin": true
        },
        "color": {
          "field": "pop2022",
          "type": "quantitative",
          "aggregate": "sum"
        }
      }
    },
    {
      "mark": "rect",
      "encoding": {
        "x": {
          "field": "gdpPerCapitaPPP",
          "type": "quantitative",
          "bin": true
        },
        "y": {
          "field": "medianIncome",
          "type": "quantitative",
          "bin": true
        },
        "color": {
          "field": "pop2022",
          "type": "quantitative",
          "aggregate": "mean"
        }
      }
    },
    {
      "mark": "rect",
      "encoding": {
        "x": {
          "field": "medianIncome",
          "type": "quantitative",
          "bin": true
        },
        "y": {
          "field": "medianIncome",
          "type": "quantitative",
          "bin": true
        },
        "color": {
          "field": "pop2022",
          "type": "quantitative",
          "aggregate": "sum"
        }
      }
    },
    {
      "mark": "rect",
      "encoding": {
        "x": {
          "field": "medianIncome",
          "type": "quantitative",
          "bin": true
        },
        "y": {
          "field": "medianIncome",
          "type": "quantitative",
          "bin": true
        },
        "color": {
          "field": "pop2022",
          "type": "quantitative",
          "aggregate": "mean"
        }
      }
    },
    {
      "mark": "rect",
      "encoding": {
        "x": {
          "field": "meanIncome",
          "type": "quantitative",
          "bin": true
        },
        "y": {
          "field": "medianIncome",
          "type": "quantitative",
          "bin": true
        },
        "color": {
          "field": "pop2022",
          "type": "quantitative",
          "aggregate": "sum"
        }
      }
    },
    {
      "mark": "rect",
      "encoding": {
        "x": {
          "field": "meanIncome",
          "type": "quantitative",
          "bin": true
        },
        "y": {
          "field": "medianIncome",
          "type": "quantitative",
          "bin": true
        },
        "color": {
          "field": "pop2022",
          "type": "quantitative",
          "aggregate": "mean"
        }
      }
    },
    {
      "mark": "rect",
      "encoding": {
        "x": {
          "field": "gdpPerCapitaPPP",
          "type": "quantitative",
          "bin": true
        },
        "y": {
          "field": "pop2022",
          "type": "quantitative",
          "bin": true
        },
        "color": {
          "field": "medianIncome",
          "type": "quantitative",
          "aggregate": "sum"
        }
      }
    },
    {
      "mark": "rect",
      "encoding": {
        "x": {
          "field": "gdpPerCapitaPPP",
          "type": "quantitative",
          "bin": true
        },
        "y": {
          "field": "pop2022",
          "type": "quantitative",
          "bin": true
        },
        "color": {
          "field": "medianIncome",
          "type": "quantitative",
          "aggregate": "mean"
        }
      }
    },
    {
      "mark": "rect",
      "encoding": {
        "x": {
          "field": "medianIncome",
          "type": "quantitative",
          "bin": true
        },
        "y": {
          "field": "pop2022",
          "type": "quantitative",
          "bin": true
        },
        "color": {
          "field": "medianIncome",
          "type": "quantitative",
          "aggregate": "sum"
        }
      }
    },
    {
      "mark": "rect",
      "encoding": {
        "x": {
          "field": "medianIncome",
          "type": "quantitative",
          "bin": true
        },
        "y": {
          "field": "pop2022",
          "type": "quantitative",
          "bin": true
        },
        "color": {
          "field": "medianIncome",
          "type": "quantitative",
          "aggregate": "mean"
        }
      }
    },
    {
      "mark": "rect",
      "encoding": {
        "x": {
          "field": "meanIncome",
          "type": "quantitative",
          "bin": true
        },
        "y": {
          "field": "pop2022",
          "type": "quantitative",
          "bin": true
        },
        "color": {
          "field": "medianIncome",
          "type": "quantitative",
          "aggregate": "sum"
        }
      }
    },
    {
      "mark": "rect",
      "encoding": {
        "x": {
          "field": "meanIncome",
          "type": "quantitative",
          "bin": true
        },
        "y": {
          "field": "pop2022",
          "type": "quantitative",
          "bin": true
        },
        "color": {
          "field": "medianIncome",
          "type": "quantitative",
          "aggregate": "mean"
        }
      }
    },
    {
      "mark": "rect",
      "encoding": {
        "x": {
          "field": "medianIncome",
          "type": "quantitative",
          "bin": true
        },
        "y": {
          "field": "gdpPerCapitaPPP",
          "type": "quantitative",
          "bin": true
        },
        "color": {
          "field": "pop2022",
          "type": "quantitative",
          "aggregate": "sum"
        }
      }
    },
    {
      "mark": "rect",
      "encoding": {
        "x": {
          "field": "medianIncome",
          "type": "quantitative",
          "bin": true
        },
        "y": {
          "field": "gdpPerCapitaPPP",
          "type": "quantitative",
          "bin": true
        },
        "color": {
          "field": "pop2022",
          "type": "quantitative",
          "aggregate": "mean"
        }
      }
    },
    {
      "mark": "rect",
      "encoding": {
        "x": {
          "field": "medianIncome",
          "type": "quantitative",
          "bin": true
        },
        "y": {
          "field": "medianIncome",
          "type": "quantitative",
          "bin": true
        },
        "color": {
          "field": "pop2022",
          "type": "quantitative",
          "aggregate": "sum"
        }
      }
    },
    {
      "mark": "rect",
      "encoding": {
        "x": {
          "field": "medianIncome",
          "type": "quantitative",
          "bin": true
        },
        "y": {
          "field": "medianIncome",
          "type": "quantitative",
          "bin": true
        },
        "color": {
          "field": "pop2022",
          "type": "quantitative",
          "aggregate": "mean"
        }
      }
    },
    {
      "mark": "rect",
      "encoding": {
        "x": {
          "field": "medianIncome",
          "type": "quantitative",
          "bin": true
        },
        "y": {
          "field": "meanIncome",
          "type": "quantitative",
          "bin": true
        },
        "color": {
          "field": "pop2022",
          "type": "quantitative",
          "aggregate": "sum"
        }
      }
    },
    {
      "mark": "rect",
      "encoding": {
        "x": {
          "field": "medianIncome",
          "type": "quantitative",
          "bin": true
        },
        "y": {
          "field": "meanIncome",
          "type": "quantitative",
          "bin": true
        },
        "color": {
          "field": "pop2022",
          "type": "quantitative",
          "aggregate": "mean"
        }
      }
    },
    {
      "mark": "rect",
      "encoding": {
        "x": {
          "field": "medianIncome",
          "type": "quantitative",
          "bin": true
        },
        "y": {
          "field": "pop2022",
          "type": "quantitative",
          "bin": true
        },
        "color": {
          "field": "gdpPerCapitaPPP",
          "type": "quantitative",
          "aggregate": "sum"
        }
      }
    },
    {
      "mark": "rect",
      "encoding": {
        "x": {
          "field": "medianIncome",
          "type": "quantitative",
          "bin": true
        },
        "y": {
          "field": "pop2022",
          "type": "quantitative",
          "bin": true
        },
        "color": {
          "field": "gdpPerCapitaPPP",
          "type": "quantitative",
          "aggregate": "mean"
        }
      }
    },
    {
      "mark": "rect",
      "encoding": {
        "x": {
          "field": "medianIncome",
          "type": "quantitative",
          "bin": true
        },
        "y": {
          "field": "pop2022",
          "type": "quantitative",
          "bin": true
        },
        "color": {
          "field": "medianIncome",
          "type": "quantitative",
          "aggregate": "sum"
        }
      }
    },
    {
      "mark": "rect",
      "encoding": {
        "x": {
          "field": "medianIncome",
          "type": "quantitative",
          "bin": true
        },
        "y": {
          "field": "pop2022",
          "type": "quantitative",
          "bin": true
        },
        "color": {
          "field": "medianIncome",
          "type": "quantitative",
          "aggregate": "mean"
        }
      }
    },
    {
      "mark": "rect",
      "encoding": {
        "x": {
          "field": "medianIncome",
          "type": "quantitative",
          "bin": true
        },
        "y": {
          "field": "pop2022",
          "type": "quantitative",
          "bin": true
        },
        "color": {
          "field": "meanIncome",
          "type": "quantitative",
          "aggregate": "sum"
        }
      }
    },
    {
      "mark": "rect",
      "encoding": {
        "x": {
          "field": "medianIncome",
          "type": "quantitative",
          "bin": true
        },
        "y": {
          "field": "pop2022",
          "type": "quantitative",
          "bin": true
        },
        "color": {
          "field": "meanIncome",
          "type": "quantitative",
          "aggregate": "mean"
        }
      }
    },
    {
      "mark": "rect",
      "encoding": {
        "x": {
          "field": "pop2022",
          "type": "quantitative",
          "bin": true
        },
        "y": {
          "field": "gdpPerCapitaPPP",
          "type": "quantitative",
          "bin": true
        },
        "color": {
          "field": "medianIncome",
          "type": "quantitative",
          "aggregate": "sum"
        }
      }
    },
    {
      "mark": "rect",
      "encoding": {
        "x": {
          "field": "pop2022",
          "type": "quantitative",
          "bin": true
        },
        "y": {
          "field": "gdpPerCapitaPPP",
          "type": "quantitative",
          "bin": true
        },
        "color": {
          "field": "medianIncome",
          "type": "quantitative",
          "aggregate": "mean"
        }
      }
    },
    {
      "mark": "rect",
      "encoding": {
        "x": {
          "field": "pop2022",
          "type": "quantitative",
          "bin": true
        },
        "y": {
          "field": "medianIncome",
          "type": "quantitative",
          "bin": true
        },
        "color": {
          "field": "medianIncome",
          "type": "quantitative",
          "aggregate": "sum"
        }
      }
    },
    {
      "mark": "rect",
      "encoding": {
        "x": {
          "field": "pop2022",
          "type": "quantitative",
          "bin": true
        },
        "y": {
          "field": "medianIncome",
          "type": "quantitative",
          "bin": true
        },
        "color": {
          "field": "medianIncome",
          "type": "quantitative",
          "aggregate": "mean"
        }
      }
    },
    {
      "mark": "rect",
      "encoding": {
        "x": {
          "field": "pop2022",
          "type": "quantitative",
          "bin": true
        },
        "y": {
          "field": "meanIncome",
          "type": "quantitative",
          "bin": true
        },
        "color": {
          "field": "medianIncome",
          "type": "quantitative",
          "aggregate": "sum"
        }
      }
    },
    {
      "mark": "rect",
      "encoding": {
        "x": {
          "field": "pop2022",
          "type": "quantitative",
          "bin": true
        },
        "y": {
          "field": "meanIncome",
          "type": "quantitative",
          "bin": true
        },
        "color": {
          "field": "medianIncome",
          "type": "quantitative",
          "aggregate": "mean"
        }
      }
    },
    {
      "mark": "rect",
      "encoding": {
        "x": {
          "field": "pop2022",
          "type": "quantitative",
          "bin": true
        },
        "y": {
          "field": "medianIncome",
          "type": "quantitative",
          "bin": true
        },
        "color": {
          "field": "gdpPerCapitaPPP",
          "type": "quantitative",
          "aggregate": "sum"
        }
      }
    },
    {
      "mark": "rect",
      "encoding": {
        "x": {
          "field": "pop2022",
          "type": "quantitative",
          "bin": true
        },
        "y": {
          "field": "medianIncome",
          "type": "quantitative",
          "bin": true
        },
        "color": {
          "field": "gdpPerCapitaPPP",
          "type": "quantitative",
          "aggregate": "mean"
        }
      }
    },
    {
      "mark": "rect",
      "encoding": {
        "x": {
          "field": "pop2022",
          "type": "quantitative",
          "bin": true
        },
        "y": {
          "field": "medianIncome",
          "type": "quantitative",
          "bin": true
        },
        "color": {
          "field": "medianIncome",
          "type": "quantitative",
          "aggregate": "sum"
        }
      }
    },
    {
      "mark": "rect",
      "encoding": {
        "x": {
          "field": "pop2022",
          "type": "quantitative",
          "bin": true
        },
        "y": {
          "field": "medianIncome",
          "type": "quantitative",
          "bin": true
        },
        "color": {
          "field": "medianIncome",
          "type": "quantitative",
          "aggregate": "mean"
        }
      }
    },
    {
      "mark": "rect",
      "encoding": {
        "x": {
          "field": "pop2022",
          "type": "quantitative",
          "bin": true
        },
        "y": {
          "field": "medianIncome",
          "type": "quantitative",
          "bin": true
        },
        "color": {
          "field": "meanIncome",
          "type": "quantitative",
          "aggregate": "sum"
        }
      }
    },
    {
      "mark": "rect",
      "encoding": {
        "x": {
          "field": "pop2022",
          "type": "quantitative",
          "bin": true
        },
        "y": {
          "field": "medianIncome",
          "type": "quantitative",
          "bin": true
        },
        "color": {
          "field": "meanIncome",
          "type": "quantitative",
          "aggregate": "mean"
        }
      }
    }
  ]
}