{
  "table_info": {
    "table_columns": [
      "ID",
      "category",
      "launched"
    ],
    "table_samples": [
      {
        "ID": 1000256230,
        "category": "Software",
        "launched": "2017-06-02 12:20:21"
      },
      {
        "ID": 854848500,
        "category": "Robots",
        "launched": "2015-04-15 18:55:04"
      },
      {
        "ID": 2130390014,
        "category": "Software",
        "launched": "2015-06-25 19:31:41"
      },
      {
        "ID": 1911398602,
        "category": "Software",
        "launched": "2012-09-07 02:10:53"
      },
      {
        "ID": 1442842816,
        "category": "Software",
        "launched": "2016-09-19 03:50:20"
      }
    ]
  },
  "nl_utterance": "Show me a line chart that displays the trend of project IDs over time, specifically for projects launched between 2013 and 2017, without considering the category to differentiate the data.",
  "refer_fileds": [
    {
      "field": "ID",
      "type": "quantitative"
    },
    {
      "field": "category",
      "type": "nominal"
    }
  ],
  "refer_others": [
    {
      "c_type": "task",
      "c_name": "trend",
      "c_list": [
        {
          "mark": [
            "bar",
            "line",
            "area"
          ],
          "encoding": {
            "x": {
              "type": "temporal"
            }
          }
        }
      ],
      "nl_ref_type": "explicit",
      "nl_ref_phrase": "..."
    },
    {
      "c_type": "mark",
      "c_name": "line chart",
      "c_list": [
        {
          "mark": "line",
          "encoding": {
            "x": {},
            "y": {
              "type": "quantitative"
            },
            "color": {
              "ignore": true,
              "type": "nominal"
            },
            "column": {
              "ignore": true,
              "type": "nominal"
            },
            "row": {
              "ignore": true,
              "type": "nominal"
            }
          },
          "unique_map": {
            "x": "y"
          }
        }
      ],
      "nl_ref_type": "explicit",
      "nl_ref_phrase": "..."
    },
    {
      "c_type": "transform",
      "c_name": "filter",
      "c_list": [
        {
          "field": "launched)",
          "gt": 2013
        }
      ],
      "nl_ref_type": "explicit",
      "nl_ref_phrase": "..."
    },
    {
      "c_type": "transform",
      "c_name": "filter",
      "c_list": [
        {
          "field": "launched)",
          "lt": 2018
        }
      ],
      "nl_ref_type": "explicit",
      "nl_ref_phrase": "..."
    }
  ],
  "generated_chart_list": [
    {
      "mark": "line",
      "encoding": {
        "x": {
          "type": "temporal",
          "field": "launched"
        },
        "y": {
          "field": "ID",
          "type": "quantitative"
        },
        "color": {
          "field": "category",
          "type": "nominal"
        }
      },
      "transform": [
        {
          "filter": {
            "field": "launched)",
            "gt": 2013
          }
        },
        {
          "filter": {
            "field": "launched)",
            "lt": 2018
          }
        }
      ]
    }
  ]
}